fps/__init__.py
fps/_config.py
fps/_context.py
fps/_importer.py
fps/_module.py
fps/_signal.py
fps/py.typed
fps/cli/_cli.py
fps/web/fastapi.py
fps/web/server.py
fps-0.5.9.dist-info/METADATA
fps-0.5.9.dist-info/WHEEL
fps-0.5.9.dist-info/entry_points.txt
fps-0.5.9.dist-info/licenses/LICENSE
fps-0.5.9.dist-info/RECORD
