Metadata-Version: 2.4
Name: fps
Version: 0.5.9
Summary: A system for creating modular, configurable, pluggable and concurrent applications
Project-URL: Source, https://github.com/jupyter-server/fps
Project-URL: Issues, https://github.com/jupyter-server/fps/issues
Author-email: Jupyter Development Team <jupyter@googlegroups.com>
License: # Licensing terms
License-File: LICENSE
Classifier: Development Status :: 4 - Beta
Classifier: Intended Audience :: Developers
Classifier: License :: OSI Approved :: BSD License
Classifier: Programming Language :: Python
Classifier: Programming Language :: Python :: 3
Classifier: Programming Language :: Python :: 3.10
Classifier: Programming Language :: Python :: 3.11
Classifier: Programming Language :: Python :: 3.12
Classifier: Programming Language :: Python :: 3.13
Classifier: Programming Language :: Python :: 3.14
Classifier: Typing :: Typed
Requires-Python: >=3.10
Requires-Dist: anyio
Requires-Dist: anyioutils<0.8.0,>=0.7.0
Requires-Dist: exceptiongroup; python_version < '3.11'
Requires-Dist: importlib-metadata>=3.6; python_version < '3.10'
Requires-Dist: structlog
Provides-Extra: anycorn
Requires-Dist: anycorn<0.19.0,>=0.18.1; extra == 'anycorn'
Provides-Extra: click
Requires-Dist: click<9,>=8.1.8; extra == 'click'
Provides-Extra: fastapi
Requires-Dist: fastapi; extra == 'fastapi'
